[{"id":"raster_form.organisation"},{"id":"raster_form.organisation_subtitle"},{"id":"raster_form.sharedOrganisation"},{"id":"raster_form.sharedOrganisation_subtitle"},{"id":"raster_form.authorization"},{"id":"raster_form.authorization_subtitle"},{"id":"raster_form.authorization_private_message"},{"id":"raster_form.authorization_common_message"},{"id":"raster_form.authorization_public_message"},{"id":"raster_form.rasterName"},{"id":"raster_form.description"},{"id":"raster_form.description_subtitle"},{"id":"raster_form.aggregation"},{"id":"raster_form.aggregation_subtitle"},{"id":"raster_form.aggregation_type_none"},{"id":"raster_form.aggregation_type_counts"},{"id":"raster_form.aggregation_type_curve"},{"id":"raster_form.aggregation_type_sum"},{"id":"raster_form.aggregation_type_average"},{"id":"raster_form.observation"},{"id":"raster_form.observation_subtitle"},{"id":"raster_form.colormap"},{"id":"raster_form.supplierName"},{"id":"raster_form.supplierName_subtitle"},{"id":"raster_form.supplierCode"},{"id":"raster_form.supplierCode_subtitle"},{"id":"raster_form.rasterSeries"},{"id":"raster_form.rasterSeries_label"},{"id":"raster_form.duration"},{"id":"raster_form.duration_subtitle"}]
